bodit_analysis_module/__init__.py
bodit_analysis_module/fhBasic.py
bodit_analysis_module/fhConst.py
bodit_analysis_module/fhDatabase.py
bodit_analysis_module/fhFeatExtractModule.py
bodit_analysis_module/fhFeature.py
bodit_analysis_module/fhRawdata.py
bodit_analysis_module-0.1.9.dist-info/METADATA
bodit_analysis_module-0.1.9.dist-info/WHEEL
bodit_analysis_module-0.1.9.dist-info/top_level.txt
bodit_analysis_module-0.1.9.dist-info/RECORD
